haretools/__init__.py
haretools/__main__.py
haretools/pipremove.py
haretools-0.1.0.dist-info/METADATA
haretools-0.1.0.dist-info/WHEEL
haretools-0.1.0.dist-info/entry_points.txt
haretools-0.1.0.dist-info/RECORD
