Metadata-Version: 2.3
Name: haretools
Version: 0.1.0
Summary: python小工具包
Author-email: Li WeiJian <1330757852@qq.com>
Classifier: License :: OSI Approved :: MIT License
Classifier: Operating System :: OS Independent
Classifier: Programming Language :: Python :: 3
Requires-Python: >=3.7
Requires-Dist: pipdeptree
